{"namedChunkGroups":{"polyfill":{"name":"polyfill","assets":[{"name":"webpack-runtime-9b1f7d5becc4ac2cb4be.js","size":3110},{"name":"polyfill-638e32c18bfed478bfe9.js","size":85292}],"filteredAssets":0,"assetsSize":88402,"filteredAuxiliaryAssets":2,"auxiliaryAssetsSize":220909},"app":{"name":"app","assets":[{"name":"webpack-runtime-9b1f7d5becc4ac2cb4be.js","size":3110},{"name":"framework-4caf031f63865f1335df.js","size":128870},{"name":"app-08d8b3714b5d85919765.js","size":49350}],"filteredAssets":0,"assetsSize":181330,"filteredAuxiliaryAssets":3,"auxiliaryAssetsSize":541504},"component---src-pages-index-js":{"name":"component---src-pages-index-js","assets":[{"name":"component---src-pages-index-js-432c849ff57967cdfb3e.js","size":335}],"filteredAssets":0,"assetsSize":335,"filteredAuxiliaryAssets":1,"auxiliaryAssetsSize":338}},"assetsByChunkName":{"polyfill":["webpack-runtime-9b1f7d5becc4ac2cb4be.js","polyfill-638e32c18bfed478bfe9.js"],"app":["webpack-runtime-9b1f7d5becc4ac2cb4be.js","framework-4caf031f63865f1335df.js","app-08d8b3714b5d85919765.js"],"component---src-pages-index-js":["component---src-pages-index-js-432c849ff57967cdfb3e.js"]},"childAssetsByChunkName":{}}